draccus/__init__.py
draccus/argparsing.py
draccus/cfgparsing.py
draccus/choice_types.py
draccus/fields.py
draccus/help_formatter.py
draccus/options.py
draccus/py.typed
draccus/utils.py
draccus/parsers/__init__.py
draccus/parsers/config_parsers.py
draccus/parsers/decoding.py
draccus/parsers/encoding.py
draccus/parsers/registry_utils.py
draccus/parsers/yaml_loader.py
draccus/wrappers/__init__.py
draccus/wrappers/choice_wrapper.py
draccus/wrappers/dataclass_wrapper.py
draccus/wrappers/docstring.py
draccus/wrappers/field_metavar.py
draccus/wrappers/field_wrapper.py
draccus/wrappers/suppressing_argparse.py
draccus/wrappers/wrapper.py
draccus-0.11.4.dist-info/licenses/LICENSE
examples/choice_class_demo.py
examples/demo.py
tests/__init__.py
tests/conftest.py
tests/test_argparse_choice_types.py
tests/test_argparse_choice_types_plugin.py
tests/test_base.py
tests/test_bools.py
tests/test_calling_using_dataclass.py
tests/test_choice_types.py
tests/test_decoding.py
tests/test_default_args.py
tests/test_docstrings.py
tests/test_encoding.py
tests/test_enums.py
tests/test_future_annotations.py
tests/test_generic_params.py
tests/test_inheritance.py
tests/test_lists.py
tests/test_literals.py
tests/test_load.py
tests/test_optional.py
tests/test_optional_choice_type.py
tests/test_optional_union.py
tests/test_preferred_help.py
tests/test_tuples.py
tests/test_union.py
tests/test_utils.py
tests/test_yaml_inclusion.py
tests/test_yaml_inclusion_cli.py
tests/testutils.py
tests/draccus_choice_plugins/gpt.py
tests/draccus_choice_plugins/model_config.py
draccus-0.11.4.dist-info/METADATA
draccus-0.11.4.dist-info/WHEEL
draccus-0.11.4.dist-info/top_level.txt
draccus-0.11.4.dist-info/RECORD
