Metadata-Version: 2.4
Name: draccus
Version: 0.11.4
Summary: A slightly opinionated framework for simple dataclass-based configurations based on Pyrallis.
Author-email: David Hall <dlwh@cs.stanford.edu>, Siddharth Karamcheti <skaramcheti@cs.stanford.edu>
License-Expression: MIT
Project-URL: homepage, https://github.com/dlwh/draccus
Project-URL: repository, https://github.com/dlwh/draccus
Project-URL: issues, https://github.com/dlwh/draccus/issues
Classifier: Development Status :: 3 - Alpha
Classifier: Operating System :: OS Independent
Classifier: Programming Language :: Python :: 3
Classifier: Programming Language :: Python :: 3.9
Classifier: Programming Language :: Python :: 3.10
Classifier: Programming Language :: Python :: 3 :: Only
Requires-Python: >=3.9
License-File: LICENSE
Requires-Dist: mergedeep~=1.3
Requires-Dist: pyyaml~=6.0
Requires-Dist: pyyaml-include~=1.4
Requires-Dist: toml~=0.10
Requires-Dist: typing-inspect~=0.9.0
Provides-Extra: dev
Requires-Dist: black; extra == "dev"
Requires-Dist: mypy; extra == "dev"
Requires-Dist: pre-commit; extra == "dev"
Requires-Dist: pytest; extra == "dev"
Requires-Dist: ruff; extra == "dev"
Dynamic: license-file
